cothority/Cothority.py
cothority/__init__.py
cothority/messages_pb2.py
cothority/network_pb2.py
cothority/status_pb2.py
cothority/websocket.py
cothority/network/__init__.py
cothority/network/network_pb2.py
cothority/skipchain/__init__.py
cothority/skipchain/methods.py
cothority/skipchain/skipchain_pb2.py
cothority/status/__init__.py
cothority/status/status_pb2.py
cothority-0.1.2.dist-info/DESCRIPTION.rst
cothority-0.1.2.dist-info/METADATA
cothority-0.1.2.dist-info/RECORD
cothority-0.1.2.dist-info/WHEEL
cothority-0.1.2.dist-info/metadata.json
cothority-0.1.2.dist-info/top_level.txt
