Metadata-Version: 2.0
Name: cothority
Version: 0.1.2
Summary: Cothority-interface for the services
Home-page: https://github.com/dedis/cothority
Author: Linus Gasser
Author-email: linus.gasser@epfl.ch
License: AGPLv3+
Keywords: cothority requests websockets
Platform: UNKNOWN
Classifier: Development Status :: 3 - Alpha
Classifier: Intended Audience :: Developers
Classifier: Topic :: Software Development :: Build Tools
Classifier: License :: OSI Approved :: GNU Affero General Public License v3 or later (AGPLv3+)
Classifier: Programming Language :: Python :: 3.5
Requires-Dist: peppercorn
Provides-Extra: dev
Requires-Dist: check-manifest; extra == 'dev'
Provides-Extra: test
Requires-Dist: coverage; extra == 'test'
